terraweave/__init__.py
terraweave/terraweave.py
terraweave-0.1.6.dist-info/licenses/LICENSE
terraweave-0.1.6.dist-info/METADATA
terraweave-0.1.6.dist-info/WHEEL
terraweave-0.1.6.dist-info/top_level.txt
terraweave-0.1.6.dist-info/RECORD
