Metadata-Version: 2.4
Name: terraweave
Version: 0.1.6
Summary: A Python wrapper for Terraform
Home-page: https://github.com/brains93/TerraWeave
Author: Grant Colgan
Author-email: grant.colgan@farsetlabs.org.uk
License: MIT
Classifier: Programming Language :: Python :: 3
Classifier: License :: OSI Approved :: MIT License
Classifier: Operating System :: OS Independent
Requires-Python: >=3.7
License-File: LICENSE
Dynamic: author
Dynamic: author-email
Dynamic: classifier
Dynamic: description
Dynamic: description-content-type
Dynamic: home-page
Dynamic: license
Dynamic: license-file
Dynamic: requires-python
Dynamic: summary
